drop/__init__.py
drop/basic.py
drop/config.py
drop/errors.py
drop/ext.py
drop/finder.py
drop/moderation.py
drop/mute.py
drop/steam.py
drop/tempban.py
drop/todo.py
drop/types.py
drop_mod-2.2.0.dist-info/LICENSE
drop_mod-2.2.0.dist-info/METADATA
drop_mod-2.2.0.dist-info/WHEEL
drop_mod-2.2.0.dist-info/top_level.txt
drop_mod-2.2.0.dist-info/zip-safe
drop_mod-2.2.0.dist-info/RECORD
