Metadata-Version: 2.1
Name: drop-mod
Version: 2.2.0
Summary: A Python moderation toolkit built for chat bots
Home-page: https://github.com/AtlasC0R3/drop-moderation
Author: atlas_core
License: Apache 2.0
Platform: UNKNOWN
Classifier: Programming Language :: Python :: 3
Requires-Python: >=3.7
License-File: LICENSE
Requires-Dist: parsedatetime (==2.6)
Requires-Dist: aiohttp (~=3.7.4)
Requires-Dist: setuptools (~=52.0.0)
Requires-Dist: bs4 (~=0.0.1)
Requires-Dist: beautifulsoup4 (~=4.9.3)
